hwfact/__init__.py
hwfact/hwfact.py
hwfact/parser.py
hwfact-0.2.0.dist-info/DESCRIPTION.rst
hwfact-0.2.0.dist-info/METADATA
hwfact-0.2.0.dist-info/RECORD
hwfact-0.2.0.dist-info/WHEEL
hwfact-0.2.0.dist-info/metadata.json
hwfact-0.2.0.dist-info/top_level.txt
