Metadata-Version: 2.0
Name: hwfact
Version: 0.2.0
Summary: From dmicode info produce a dataset
Home-page: https://github.com/KhalidCK/hwfact
Author: Khalid Chakhmoun
Author-email: fr.ckhalid@gmail.com
License: UNKNOWN
Keywords: hwfact
Platform: UNKNOWN
Classifier: Development Status :: 2 - Pre-Alpha
Classifier: Intended Audience :: Developers
Classifier: Natural Language :: English
Classifier: Programming Language :: Python :: 3.6
Requires-Dist: Click (>=6.0)
